httpsrvvcr/__init__.py
httpsrvvcr/player.py
httpsrvvcr/recorder.py
httpsrvvcr-0.1.9.dist-info/DESCRIPTION.rst
httpsrvvcr-0.1.9.dist-info/METADATA
httpsrvvcr-0.1.9.dist-info/RECORD
httpsrvvcr-0.1.9.dist-info/WHEEL
httpsrvvcr-0.1.9.dist-info/metadata.json
httpsrvvcr-0.1.9.dist-info/top_level.txt
