Metadata-Version: 2.0
Name: httpsrvvcr
Version: 0.1.9
Summary: VCR recording proxy-server for usage with httpsrv
Home-page: https://github.com/2gis/httpsrvvcr
Author: 2GIS
Author-email: a.nyrkov@2gis.ru
License: MIT
Keywords: api http mock testing vcr
Platform: UNKNOWN
Classifier: Development Status :: 3 - Alpha
Classifier: Intended Audience :: Developers
Classifier: Topic :: Software Development :: Testing
Classifier: License :: OSI Approved :: MIT License
Classifier: Programming Language :: Python :: 3
Classifier: Programming Language :: Python :: 3.3
Classifier: Programming Language :: Python :: 3.4
Classifier: Programming Language :: Python :: 3.5
Requires-Dist: tornado
Requires-Dist: pyyaml
Requires-Dist: httpsrv
Provides-Extra: test
Requires-Dist: requests; extra == 'test'
